<annotation>
	<folder>Dataset</folder>
	<filename>B13.jpg</filename>
	<path>/home/tirth211/Desktop/EvilPortImgDetection/Temp/Object_Detection/Dataset/B13.jpg</path>
	<source>
		<database>Unknown</database>
	</source>
	<size>
		<width>200</width>
		<height>200</height>
		<depth>3</depth>
	</size>
	<segmented>0</segmented>
	<object>
		<name>ASL_B</name>
		<pose>Unspecified</pose>
		<truncated>0</truncated>
		<difficult>0</difficult>
		<bndbox>
			<xmin>123</xmin>
			<ymin>38</ymin>
			<xmax>193</xmax>
			<ymax>199</ymax>
		</bndbox>
	</object>
</annotation>
